nlip_server/__init__.py
nlip_server/echo.py
nlip_server/routes/__init__.py
nlip_server/routes/health.py
nlip_server/routes/nlip.py
nlip_server/server.py
nlip_server-0.1.2.dist-info/LICENSE
nlip_server-0.1.2.dist-info/METADATA
nlip_server-0.1.2.dist-info/WHEEL
nlip_server-0.1.2.dist-info/entry_points.txt
nlip_server-0.1.2.dist-info/RECORD
