Metadata-Version: 2.3
Name: nlip-server
Version: 0.1.2
Summary: 
Author: Dinesh Verma
Author-email: dverma@us.ibm.com
Requires-Python: >=3.10,<4.0
Classifier: Programming Language :: Python :: 3
Classifier: Programming Language :: Python :: 3.10
Classifier: Programming Language :: Python :: 3.11
Classifier: Programming Language :: Python :: 3.12
Classifier: Programming Language :: Python :: 3.13
Requires-Dist: fastapi[standard] (>=0.115.12,<0.116.0)
Requires-Dist: nlip-sdk (>=0.1.2,<0.2.0)
